venus_dashboard/__init__.py
venus_dashboard/api/__init__.py
venus_dashboard/api/venus.py
venus_dashboard/api/venus_rest_api.py
venus_dashboard/configuration/__init__.py
venus_dashboard/configuration/panel.py
venus_dashboard/configuration/urls.py
venus_dashboard/configuration/views.py
venus_dashboard/configuration/templates/configuration/index.html
venus_dashboard/enabled/_4050_admin_venus_panel_group.py
venus_dashboard/enabled/_4060_admin_add_log_search_panel.py
venus_dashboard/enabled/_4061_admin_add_log_analysis_panel.py
venus_dashboard/enabled/_4062_admin_add_log_error_panel.py
venus_dashboard/enabled/_4069_admin_add_configuration_panel.py
venus_dashboard/enabled/_4070_admin_add_log_detect_panel.py
venus_dashboard/log_analysis/__init__.py
venus_dashboard/log_analysis/panel.py
venus_dashboard/log_analysis/tests.py
venus_dashboard/log_analysis/urls.py
venus_dashboard/log_analysis/views.py
venus_dashboard/log_analysis/templates/log_analysis/index.html
venus_dashboard/log_detect/__init__.py
venus_dashboard/log_detect/panel.py
venus_dashboard/log_detect/tests.py
venus_dashboard/log_detect/urls.py
venus_dashboard/log_detect/views.py
venus_dashboard/log_detect/templates/log_detect/index.html
venus_dashboard/log_error/__init__.py
venus_dashboard/log_error/panel.py
venus_dashboard/log_error/urls.py
venus_dashboard/log_error/views.py
venus_dashboard/log_error/templates/log_error/index.html
venus_dashboard/log_search/__init__.py
venus_dashboard/log_search/panel.py
venus_dashboard/log_search/tests.py
venus_dashboard/log_search/urls.py
venus_dashboard/log_search/views.py
venus_dashboard/log_search/templates/log_search/index.html
venus_dashboard/static/app/core/openstack-service-api/venus.service.js
venus_dashboard/static/dashboard/admin/venus.module.js
venus_dashboard/static/dashboard/admin/services/venus.service.js
venus_dashboard/static/dashboard/admin/venus/configuration/configuration.controller.js
venus_dashboard-7.0.0.dist-info/AUTHORS
venus_dashboard-7.0.0.dist-info/LICENSE
venus_dashboard-7.0.0.dist-info/METADATA
venus_dashboard-7.0.0.dist-info/WHEEL
venus_dashboard-7.0.0.dist-info/pbr.json
venus_dashboard-7.0.0.dist-info/top_level.txt
venus_dashboard-7.0.0.dist-info/RECORD
