Metadata-Version: 2.1
Name: venus-dashboard
Version: 7.0.0
Summary: Venus Horizon plugin
Home-page: https://docs.openstack.org/venus-dashboard/latest/
Author: OpenStack
Author-email: openstack-discuss@lists.openstack.org
Classifier: Environment :: OpenStack
Classifier: Intended Audience :: Information Technology
Classifier: Intended Audience :: System Administrators
Classifier: License :: OSI Approved :: Apache Software License
Classifier: Operating System :: POSIX :: Linux
Classifier: Programming Language :: Python
Classifier: Programming Language :: Python :: Implementation :: CPython
Classifier: Programming Language :: Python :: 3 :: Only
Classifier: Programming Language :: Python :: 3
Classifier: Programming Language :: Python :: 3.8
Classifier: Programming Language :: Python :: 3.9
Classifier: Programming Language :: Python :: 3.10
Classifier: Programming Language :: Python :: 3.11
Requires-Python: >=3.8
License-File: LICENSE
License-File: AUTHORS
Requires-Dist: pbr !=2.1.0,>=2.0.0
Requires-Dist: django-compressor >=2.0
Requires-Dist: iso8601 >=0.1.11
Requires-Dist: horizon >=17.1.0
Requires-Dist: oslo.context >=2.9.0
Requires-Dist: oslo.policy >=3.7.0
Requires-Dist: XStatic-Angular >=1.5.8.0
Requires-Dist: XStatic-Angular-Bootstrap >=2.2.0.0
Requires-Dist: XStatic-Bootstrap-Datepicker >=1.3.1.0
Requires-Dist: XStatic-Bootstrap-SCSS >=3.3.7.1
Requires-Dist: XStatic-Dagre >=0.6.4.0
Requires-Dist: XStatic-Dagre-D3 >=0.4.17.0
Requires-Dist: XStatic-D3 >=3.5.17.0
Requires-Dist: XStatic-Font-Awesome >=4.7.0.0
Requires-Dist: XStatic-Graphlib >=2.1.7.0
Requires-Dist: XStatic-jQuery >=1.8.2.1
Requires-Dist: XStatic-lodash >=4.16.4.1
Requires-Dist: XStatic-moment >=2.8.4.1
Requires-Dist: XStatic-Moment-Timezone >=0.5.22.0
Requires-Dist: XStatic-smart-table >=1.4.13.2
